hw3/hw3_part_1/lab3_1.v
`timescale 1ns / 1ps

module sf(
    input S,
    input F,
    input clk,
    output reg Q
    );

    initial begin
        Q = 0;
    end
	
    // write your code here
    always @(posedge clk) begin
        case ({S,F})
        
           2'b00: Q<=1'b0;
           2'b01: Q<=1'b1;
           2'b10: Q<=Q;
           2'b11: Q<=~Q;
        endcase
    end
	 
endmodule

module ic1500(
    input B, 
    input A, 
    input X, 
	 input clk,
	 output D0,
	 output D1,
	 output Q,
    output Z
    );
    // write your code here
    wire C1 = A & ~B & ~X,
         C2 = ~A & B & ~X,
         C3 = A & ~B;
         
    assign D0 = C3 | X,
    D1 = C1 | C2;

    sf sf_a(
        .S(D1),
        .F(D0),
        .clk(clk),
        .Q(Q)
    );

    assign Z = Q & X;
endmodule

hw3/hw3_part_1/testbench_sf.v
`timescale 1ns / 1ps
module test_sf;

	// Inputs
	reg S;
	reg F;
	reg clk;

	// Outputs
	wire Q;

	// Instantiate the Unit Under Test (UUT)
	sf uut (
		.S(S), 
		.F(F), 
		.clk(clk),
		.Q(Q)
	);
    
    // At 5, 15, 25, .. clk will change 1->0 
    // At 10, 20, 30, .. clk will change 0->1
    initial clk = 1;
	always #5 clk = ~clk;

	initial begin
        $dumpfile("testbench_sf.vcd"); 
        $dumpvars(0, test_sf);
		// set monitor to inputs and outputs
		$monitor("Time=%t | S=%b F=%b| Q=%b", $time, S, F, Q);
		
        
		// Initialize Inputs
		S = 0;
		F = 0;

		// Wait 5 ns for global reset to finish
		#5;
        
		// Add stimulus here
        
		S= 0; F= 1;
		#10; // Wait for clock edge
		if (Q != 1) $display("Value of Q after S= 0 F= 1 is wrong");
		else $display("Successful");
		S= 1; F= 1;
		#10; // Wait for clock edge
		if (Q != 0) $display("Value of Q after S= 1 F= 1 is wrong");
		else $display("Successful");
		S= 0; F= 1;
		#10; // Wait for clock edge
		if (Q != 1) $display("Value of Q after S= 0 F= 1 is wrong");
		else $display("Successful");
		S= 1; F= 0;
		#10; // Wait for clock edge
		if (Q != 1) $display("Value of Q after S= 1 F= 0 is wrong");
		else $display("Successful");
		S= 0; F= 0;
		#10; // Wait for clock edge
		if (Q != 0) $display("Value of Q after S= 0 F= 1 is wrong");
		else $display("Successful");
		S= 1; F= 1;
		#10; // Wait for clock edge
		if (Q != 1) $display("Value of Q after S= 1 F= 1 is wrong");
		else $display("Successful");
		$finish;
        
	end
      
endmodule

hw3/hw3_part_1/testbench_sf.vcd
$date
	Fri Apr  3 23:34:42 2020
$end
$version
	Icarus Verilog
$end
$timescale
	1ps
$end
$scope module test_sf $end
$var wire 1 ! Q $end
$var reg 1 " F $end
$var reg 1 # S $end
$var reg 1 $ clk $end
$scope module uut $end
$var wire 1 " F $end
$var wire 1 # S $end
$var wire 1 $ clk $end
$var reg 1 ! Q $end
$upscope $end
$upscope $end
$enddefinitions $end
#0
$dumpvars
1$
0#
0"
0!
$end
#5000
1"
0$
#10000
1!
1$
#15000
0$
1#
#20000
0!
1$
#25000
0$
0#
#30000
1!
1$
#35000
0$
0"
1#
#40000
1$
#45000
0$
0#
#50000
0!
1$
#55000
0$
1"
1#
#60000
1!
1$
