hw3/hw3_part_1/lab3_1.v
`timescale 1ns / 1ps

module sf(
    input S,
    input F,
    input clk,
    output reg Q
    );

    initial begin
        Q = 0;
    end
	
    // write your code here
    always @(posedge clk) begin
        case ({S,F})
        
           2'b00: Q<=1'b0;
           2'b01: Q<=1'b1;
           2'b10: Q<=Q;
           2'b11: Q<=~Q;
        endcase
    end
	 
endmodule

module ic1500(
    input B, 
    input A, 
    input X, 
	 input clk,
	 output D0,
	 output D1,
	 output Q,
    output Z
    );
    // write your code here
    wire C1 = A & ~B & ~X,
         C2 = ~A & B & ~X,
         C3 = A & ~B;
         
    assign D0 = C3 | X,
    D1 = C1 | C2;

    sf sf_a(
        .S(D1),
        .F(D0),
        .clk(clk),
        .Q(Q)
    );

    assign Z = Q & X;
endmodule

hw3/hw3_part_1/testbench_ic1500_utku.v
`timescale 1ns / 1ps

module testbench_ic1500;

	// Inputs
	reg B;
	reg A;
	reg X;
	reg clk;

	// Outputs
	wire D0;
	wire D1;
	wire Q;
	wire Z;

	// Instantiate the Unit Under Test (UUT)
	ic1500 uut (
		.B(B), 
		.A(A), 
		.X(X),
		.clk(clk),
		.D0(D0), 
		.D1(D1), 
		.Q(Q),
		.Z(Z)
	);

	// At 5, 15, 25, .. clk will change 1->0 
    // At 10, 20, 30, .. clk will change 0->1
    initial clk = 1;
	always #5 clk = ~clk;

	initial begin
		$dumpfile("testbench_ic1500.vcd"); 
        $dumpvars(0, testbench_ic1500);
		// set monitor to inputs and outputs
		$monitor("Time=%t | A=%b B=%b X=%b| D0=%b D1=%b Q=%b Z=%b", $time, A, B, X, D0, D1, Q, Z);
		
        
		// Initialize Inputs
		A = 0; B = 0; X = 0;

		// Wait 5 ns for global reset to finish
		#5;
		// Add stimulus here
		A = 0; B = 0; X = 0;
		#10; // Wait for clock edge
		$display("Now A=%b B=%b X=%b, results should be D0=0 D1=0 Q=0 Z=0", A, B, X);
		if(D0!=0 || D1!=0 || Q!=0 || Z!=0) $display("Before checking others, correct this case. Rest of the test depends on this");
		else $display("Successful");
		
		A = 0; B = 0; X = 1;
		#10; // Wait for clock edge
		$display("Now A=%b B=%b X=%b, results should be D0=1 D1=0 Q=1 Z=1", A, B, X);
		if(D0!=1 || D1!=0 || Q!=1 || Z!=1) $display("Before checking others, correct this case. Rest of the test depends on this");
		else $display("Successful");
		
		
		
		A = 0; B = 0; X = 0;
		#10; // Wait for clock edge
		
		A = 0; B = 0; X = 0;
		#10; // Wait for clock edge
		$display("After Q=0, now A=%b B=%b X=%b, results should be D0=0 D1=0 Q=0 Z=0", A, B, X);
		if(D0!=0 || D1!=0 || Q!=0 || Z!=0) $display("Wrong");
		else $display("Successful");
		
		A = 0; B = 0; X = 1;
		#10; // Wait for clock edge
		
		A = 0; B = 0; X = 0;
		#10; // Wait for clock edge
		$display("After Q=1, now A=%b B=%b X=%b, results should be D0=0 D1=0 Q=0 Z=0", A, B, X);
		if(D0!=0 || D1!=0 || Q!=0 || Z!=0) $display("Wrong");
		else $display("Successful");		
		
		
		A = 0; B = 0; X = 0;
		#10; // Wait for clock edge
		
		A = 0; B = 0; X = 1;
		#10; // Wait for clock edge
		$display("After Q=0, now A=%b B=%b X=%b, results should be D0=1 D1=0 Q=1 Z=1", A, B, X);
		if(D0!=1 || D1!=0 || Q!=1 || Z!=1) $display("Wrong");
		else $display("Successful");
		
		A = 0; B = 0; X = 1;
		#10; // Wait for clock edge
		
		A = 0; B = 0; X = 1;
		#10; // Wait for clock edge
		$display("After Q=1, now A=%b B=%b X=%b, results should be D0=1 D1=0 Q=1 Z=1", A, B, X);
		if(D0!=1 || D1!=0 || Q!=1 || Z!=1) $display("Wrong");
		else $display("Successful");
		
		
		A = 0; B = 0; X = 0;
		#10; // Wait for clock edge
		
		A = 0; B = 1; X = 0;
		#10; // Wait for clock edge
		$display("After Q=0, now A=%b B=%b X=%b, results should be D0=0 D1=1 Q=0 Z=0", A, B, X);
		if(D0!=0 || D1!=1 || Q!=0 || Z!=0) $display("Wrong");
		else $display("Successful");
		
		A = 0; B = 0; X = 1;
		#10; // Wait for clock edge
		
		A = 0; B = 1; X = 0;
		#10; // Wait for clock edge
		$display("After Q=1, now A=%b B=%b X=%b, results should be D0=0 D1=1 Q=1 Z=0", A, B, X);
		if(D0!=0 || D1!=1 || Q!=1 || Z!=0) $display("Wrong");
		else $display("Successful");
		
		
		A = 0; B = 0; X = 0;
		#10; // Wait for clock edge
		
		A = 0; B = 1; X = 1;
		#10; // Wait for clock edge
		$display("After Q=0, now A=%b B=%b X=%b, results should be D0=1 D1=0 Q=1 Z=1", A, B, X);
		if(D0!=1 || D1!=0 || Q!=1 || Z!=1) $display("Wrong");
		else $display("Successful");
		
		A = 0; B = 0; X = 1;
		#10; // Wait for clock edge
		
		A = 0; B = 1; X = 1;
		#10; // Wait for clock edge
		$display("After Q=1, now A=%b B=%b X=%b, results should be D0=1 D1=0 Q=1 Z=1", A, B, X);
		if(D0!=1 || D1!=0 || Q!=1 || Z!=1) $display("Wrong");
		else $display("Successful");		


		A = 0; B = 0; X = 0;
		#10; // Wait for clock edge
		
		A = 1; B = 0; X = 0;
		#10; // Wait for clock edge
		$display("After Q=0, now A=%b B=%b X=%b, results should be D0=1 D1=1 Q=1 Z=0", A, B, X);
		if(D0!=1 || D1!=1 || Q!=1 || Z!=0) $display("Wrong");
		else $display("Successful");
		
		A = 0; B = 0; X = 1;
		#10; // Wait for clock edge
		
		A = 1; B = 0; X = 0;
		#10; // Wait for clock edge
		$display("After Q=1, now A=%b B=%b X=%b, results should be D0=1 D1=1 Q=0 Z=0", A, B, X);
		if(D0!=1 || D1!=1 || Q!=0 || Z!=0) $display("Wrong");
		else $display("Successful");		
		
		
		A = 0; B = 0; X = 0;
		#10; // Wait for clock edge
		
		A = 1; B = 0; X = 1;
		#10; // Wait for clock edge
		$display("After Q=0, now A=%b B=%b X=%b, results should be D0=1 D1=0 Q=1 Z=1", A, B, X);
		if(D0!=1 || D1!=0 || Q!=1 || Z!=1) $display("Wrong");
		else $display("Successful");
		
		A = 0; B = 0; X = 1;
		#10; // Wait for clock edge
		
		A = 1; B = 0; X = 1;
		#10; // Wait for clock edge
		$display("After Q=1, now A=%b B=%b X=%b, results should be D0=1 D1=0 Q=1 Z=1", A, B, X);
		if(D0!=1 || D1!=0 || Q!=1 || Z!=1) $display("Wrong");
		else $display("Successful");
		
		
		A = 0; B = 0; X = 0;
		#10; // Wait for clock edge
		
		A = 1; B = 1; X = 0;
		#10; // Wait for clock edge
		$display("After Q=0, now A=%b B=%b X=%b, results should be D0=0 D1=0 Q=0 Z=0", A, B, X);
		if(D0!=0 || D1!=0 || Q!=0 || Z!=0) $display("Wrong");
		else $display("Successful");
		
		A = 0; B = 0; X = 1;
		#10; // Wait for clock edge
		
		A = 1; B = 1; X = 0;
		#10; // Wait for clock edge
		$display("After Q=1, now A=%b B=%b X=%b, results should be D0=0 D1=0 Q=0 Z=0", A, B, X);
		if(D0!=0 || D1!=0 || Q!=0 || Z!=0) $display("Wrong");
		else $display("Successful");
		
		
		A = 0; B = 0; X = 0;
		#10; // Wait for clock edge
		
		A = 1; B = 1; X = 1;
		#10; // Wait for clock edge
		$display("After Q=0, now A=%b B=%b X=%b, results should be D0=1 D1=0 Q=1 Z=1", A, B, X);
		if(D0!=1 || D1!=0 || Q!=1 || Z!=1) $display("Wrong");
		else $display("Successful");
		
		A = 0; B = 0; X = 1;
		#10; // Wait for clock edge
		
		A = 1; B = 1; X = 1;
		#10; // Wait for clock edge
		$display("After Q=1, now A=%b B=%b X=%b, results should be D0=1 D1=0 Q=1 Z=1", A, B, X);
		if(D0!=1 || D1!=0 || Q!=1 || Z!=1) $display("Wrong");
		else $display("Successful");		



		$finish;
	end
      
endmodule

hw3/hw3_part_1/testbench_ic1500.vcd
$date
	Sun Apr  5 19:33:02 2020
$end
$version
	Icarus Verilog
$end
$timescale
	1ps
$end
$scope module testbench_ic1500 $end
$var wire 1 ! Z $end
$var wire 1 " Q $end
$var wire 1 # D1 $end
$var wire 1 $ D0 $end
$var reg 1 % A $end
$var reg 1 & B $end
$var reg 1 ' X $end
$var reg 1 ( clk $end
$scope module uut $end
$var wire 1 % A $end
$var wire 1 & B $end
$var wire 1 ) C1 $end
$var wire 1 * C2 $end
$var wire 1 + C3 $end
$var wire 1 $ D0 $end
$var wire 1 # D1 $end
$var wire 1 ' X $end
$var wire 1 ! Z $end
$var wire 1 ( clk $end
$var wire 1 " Q $end
$scope module sf_a $end
$var wire 1 $ F $end
$var wire 1 # S $end
$var wire 1 ( clk $end
$var reg 1 " Q $end
$upscope $end
$upscope $end
$upscope $end
$enddefinitions $end
#0
$dumpvars
0+
0*
0)
1(
0'
0&
0%
0$
0#
0"
0!
$end
#5000
0(
#10000
1(
#15000
1$
0(
1'
#20000
1!
1"
1(
#25000
0$
0!
0(
0'
#30000
0"
1(
#35000
0(
#40000
1(
#45000
1$
0(
1'
#50000
1!
1"
1(
#55000
0$
0!
0(
0'
#60000
0"
1(
#65000
0(
#70000
1(
#75000
1$
0(
1'
#80000
1!
1"
1(
#85000
0(
#90000
1(
#95000
0(
#100000
1(
#105000
0$
0!
0(
0'
#110000
0"
1(
#115000
1#
1*
0(
1&
#120000
1(
#125000
0#
0*
1$
0(
1'
0&
#130000
1!
1"
1(
#135000
1#
1*
0$
0!
0(
0'
1&
#140000
1(
#145000
0#
0*
0(
0&
#150000
0"
1(
#155000
1$
0(
1'
1&
#160000
1!
1"
1(
#165000
0(
0&
#170000
1(
#175000
0(
1&
#180000
1(
#185000
0$
0!
0(
0'
0&
#190000
0"
1(
#195000
1#
1$
1)
1+
0(
1%
#200000
1"
1(
#205000
0#
0)
1!
0+
0(
1'
0%
#210000
1(
#215000
1#
1)
0!
1+
0(
0'
1%
#220000
0"
1(
#225000
0#
0$
0)
0+
0(
0%
#230000
1(
#235000
1$
1+
0(
1'
1%
#240000
1!
1"
1(
#245000
0+
0(
0%
#250000
1(
#255000
1+
0(
1%
#260000
1(
#265000
0$
0!
0+
0(
0'
0%
#270000
0"
1(
#275000
0#
0$
0)
0+
0(
1&
1%
#280000
1(
#285000
1$
0(
1'
0&
0%
#290000
1!
1"
1(
#295000
0$
0#
0)
0!
0+
0(
0'
1&
1%
#300000
0"
1(
#305000
0(
0&
0%
#310000
1(
#315000
1$
0+
0(
1'
1&
1%
#320000
1!
1"
1(
#325000
0(
0&
0%
#330000
1(
#335000
0+
0(
1&
1%
